{
  "main": {
    "name":" Francisco Guedes",
    "occupation":" junior developer and data analyst enthusiast",
    "description":"currently working @ TP in",
    "image":"profilepic.jpg",
    "bio":"Passionate about technology and programming, I have been looking for training in this area. My entire professional experience has been focused on Customer Centric and problem solving with a strong commitment to customer satisfaction. From 2012 untill 2020 worked in the Tourism and Hospitality sector in award winning establishments all over Europe. Currently working in Teleperformance, Lisbon, seeking a Junior Developer position to leverage my professional expertise and career. In my spare time I'm working on my side projects as a programmer, listening to Economic and Financial podcasts, reading about inspiring world leaders and working on my mind and body.",
    "contactmessage":"Here is where you should write your message to readers to have them get in contact with you.",
    "email": "franciscojmguedes@gmail.com",
    "phone": "+351 960213927",
    "address":{
      "city":"Lisbon",
      "zip": "Portugal"
    },
    "website": "http://www.",
    "resumedownload":"./images/Francisco_Guedes_CV_ENG.pdf",
    "social":[
      {
        "name":"twitter",
        "url":"https://twitter.com/FrancisBits",
        "className":"fa fa-twitter"
      },
      {
        "name":"linkedin",
        "url":"https://www.linkedin.com/in/franciscojmguedes/",
        "className":"fa fa-linkedin"
      },
      {
        "name":"instagram",
        "url":"https://www.instagram.com/farawei/?hl=pt",
        "className":"fa fa-instagram"
      },
      {
        "name":"github",
        "url":"https://github.com/FrancisGuedes",
        "className":"fa fa-github"
      },
      {
        "name":"skype",
        "url":"https://web.skype.com/",
        "className":"fa fa-skype"
      }
    ]
  },
  "resume":{
    "skillmessage":"Please be aware that I'm mostly a self-thaught programmer",
    "education":[
      {
        "school":"Instituto Superior de Economia e Gestão, Lisbon",
        "degree":"Post-Graduation in Digital Technologies for Management",
        "graduated":"2020 - 2021",
        "description":"Agile Methods - Agile Project Management - Competitive Intelligence - Cloud Computing Tools and Application - Data Base Management (SQL) - Information Systems Security - Design Thinking - Business Analytics (Power BI) - Software Development (Python) - Software Development Project (Django) - Digital Transformation Strategy - Consulting in Digital Management"
      },
      {
        "school":"Instituto Superior de Gestão, Lisbon",
        "degree":"Post-Graduation in Business Management",
        "graduated":"2019 - 2020",
        "description":"Strategic Business - Organization Behavior - Business Competitiveness - International Marketing - Finance Management - Economy - Business Ethnics - Analysis of Project Investements - Logistics and Operations - Capital Market"
      },
      {
        "school":"Codecademy",
        "degree":"Certification Web Developement",
        "graduated":"2020",
        "description":"HTML - CSS - GIT - Java Script OOP - Async Js and HTTPS Requests - JSON - Test Driven Development - React JSX, Components, Hooks - Redux - Relational Data Structures SQL - RESTful APIs - Node.js - Express.js"
      },
      {
        "school":"Escola de Hotelaria e Turismo de Coimbra",
        "degree":"Hospitality Management",
        "graduated":"2012 - 2014",
        "description":""
      }
    ],
    "work":[
      {
        "company":"Teleperformance, Lisbon",
        "title":"Help Desk / Customer Service",
        "years":"April 2020 - Present",
        "description":"Help Desk / Customer Support in English via chat, email and inbound calls on Netflix and FootLocker projects"
      },
      {
        "company":"Fauna & Flora, Lisbon",
        "title":"Manager",
        "years":"October 2019 - April 2020",
        "description":"Team leader of 14 people where I managed and monitored all the consumer goods, food costs, events, menus and suppliers."
      },
      {
        "company":"Fava Tonka, Oporto",
        "title":"Manager",
        "years":"May 2019 - October 2019",
        "description":"Responsible for the restaurant with a team of 9 where I supervised and managed all consumer goods, stocks, variable costs, events, menus and suppliers."
      }
    ],
    "skills":[
      {
        "name":"Git",
        "level":"30%"
      },
      {
        "name":"HTML5 / CSS / JS",
        "level":"55%"
      },
      {
        "name":"ReactJs",
        "level":"50%"
      },
      {
        "name":"Django",
        "level":"40%"
      },
      {
        "name":"SQL",
        "level":"50%"
      },
      {
        "name":"Python",
        "level":"55%"
      },
      {
        "name":"Power BI",
        "level":"40%"
      }
    ]
  },
  "portfolio":{
    "projects": [
      {
        "title":"First Steps Digital Edition",
        "category":"Website event of an NPO",
        "image":"canadian-wanderlust.jpg",
        "url":"https://github.com/FrancisGuedes/FirstSteps-DigitalEdition"
      },
      {
        "title":"Art On A Plate",
        "category":"Try to not get mouth watering",
        "image":"fury-fighting-gear.jpg",
        "url":"https://www.canva.com/design/DADhWy94a9U/view?utm_content=DADhWy94a9U&utm_campaign=designshare&utm_medium=link&utm_source=publishsharelink"
      },
      {
        "title":"Mind and Body",
        "category":"Art and Body",
        "image":"original-thai-food.jpg",
        "url":"https://www.canva.com/design/DAEYp24_UIY/_cg819V4I8uL-ZJYlAT3Xg/watch?utm_content=DAEYp24_UIY&utm_campaign=designshare&utm_medium=link&utm_source=publishsharelink"
      },
      {
        "title":"Mind and body",
        "category":"Art And Body",
        "image":"resume-website.jpg",
        "url":""
      },
      {
        "title":"Smirkspace",
        "category":"(MVP Only) A React and Meteor based chat University project.",
        "image":"smirkspace.jpg",
        "url":""
      }
    ]
  },
  "testimonials":{
    "testimonials":[
      {
        "text":"Work fast and get shit done.",
        "user":"Tourism and Hospitality Sector"
      },
      {
        "text":"That Tim Baker must be one of the most brilliant developers I've ever met! It is amazing that nobody has hired him yet. Hey you, you should hire this guy, he may be fresh out of University and have zero on the job experience but I am confident that he will be one of your best developers in no time!",
        "user":"Steve Wozniak... impersonator"
      }
    ]
  }
}
